{
  "社会・公共": {
    "description": "社会の仕組みや公共性に関わる領域。政治・行政・経済をはじめ、国や社会全体を支える制度や問題、公共の利益に関するテーマなどを扱う。",
    "subcategories": [
      {
        "category": "政治",
        "description": "国家の統治や政策決定など、社会を運営する仕組みを研究・実践する領域。"
      },
      {
        "category": "行政",
        "description": "政治に基づく施策を具体的に実行・運営し、公共サービスを提供する機構やシステムに関する領域。"
      },
      {
        "category": "政策",
        "description": "公共の課題や目的を達成するための計画や施策の立案・実行を扱う領域。"
      },
      {
        "category": "法律",
        "description": "社会秩序を維持するためのルールや規範を定める仕組み、およびその運用に関する領域。"
      },
      {
        "category": "司法",
        "description": "法律を適用して争いや違反を解決・裁定する機関や制度に関する領域。"
      },
      {
        "category": "倫理",
        "description": "社会的・公共的な視点から、人々の行動や判断の基準となる規範を探究する領域。"
      },
      {
        "category": "経済",
        "description": "資源配分や生産・消費など、社会を循環させる仕組み全般を扱う領域。"
      },
      {
        "category": "金融",
        "description": "資金の流通や管理、投資、銀行・証券・保険などのサービス・制度を扱う領域。"
      },
      {
        "category": "産業",
        "description": "経済活動の中で行われる製品・サービスの生産やビジネス展開に関する領域。"
      },
      {
        "category": "国",
        "description": "国家という単位での社会的組織や制度、国民と政府との関係などを扱う領域。"
      },
      {
        "category": "外交",
        "description": "国際関係において、国家間の協力や交渉、国益を調整する活動を扱う領域。"
      },
      {
        "category": "安全保障",
        "description": "国家や地域の安全を守るための軍事・外交・情報政策などに関する領域。"
      },
      {
        "category": "労働",
        "description": "人々の就業形態や雇用関係、働く環境、労働条件などを扱う領域。"
      },
      {
        "category": "社会",
        "description": "人々の生活やコミュニティ、社会問題、社会構造など多様な観点を含む広域的な領域。"
      },
      {
        "category": "人権",
        "description": "個人が持つ基本的な権利・自由を守るための理念や制度、問題意識に関する領域。"
      },
      {
        "category": "福祉",
        "description": "高齢者・障がい者・子どもなどを含むすべての人々の生活を支援する仕組みや制度を扱う領域。"
      },
      {
        "category": "ジェンダー",
        "description": "社会や文化における性差・性役割に関する問題・課題・平等を扱う領域。"
      },
      {
        "category": "防災",
        "description": "自然災害や事故などによる被害を最小限に抑えるための対策や準備を扱う領域。"
      },
      {
        "category": "危機管理",
        "description": "さまざまな脅威やリスクに対処し、被害を抑え迅速に復旧するための組織的取り組みを扱う領域。"
      },
      {
        "category": "思想",
        "description": "人間や社会に関する体系的な考え方や哲学的基盤などを探究する領域。"
      },
      {
        "category": "宗教",
        "description": "超越的な存在や信仰・儀礼・教義など、人間の精神文化の重要要素を扱う領域。"
      },
      {
        "category": "哲学",
        "description": "実在や価値、認識など根本的な問題について理性的に考察する学問領域。"
      }
    ]
  },
  "自然・科学・技術": {
    "description": "自然界や宇宙の仕組み、科学的な原理や実証、そして技術開発や工学的アプローチなどに関する領域。",
    "subcategories": [
      {
        "category": "自然",
        "description": "山・海・川など、人間の手が加わっていない環境や生態系を扱う領域。"
      },
      {
        "category": "環境",
        "description": "自然環境や資源の保護・管理、持続可能性などを包括的に考察する領域。"
      },
      {
        "category": "生態学",
        "description": "生物と環境の相互作用や生態系の構造・機能を研究する領域。"
      },
      {
        "category": "気候変動",
        "description": "地球規模での気候変動やその原因・影響、対策などを扱う領域。"
      },
      {
        "category": "宇宙",
        "description": "地球外の空間全体、惑星・恒星など天体を含む広大な領域。"
      },
      {
        "category": "天文学",
        "description": "宇宙や天体の観測と理論を通じて、その構造や進化を研究する科学領域。"
      },
      {
        "category": "数学",
        "description": "数量・空間・構造などに関する理論体系であり、多分野の基盤となる領域。"
      },
      {
        "category": "物理学",
        "description": "物質やエネルギーの基本的性質・法則を探究し、自然界の根本を理解する科学領域。"
      },
      {
        "category": "化学",
        "description": "物質の構造や性質、変化のしくみを解明する科学領域。"
      },
      {
        "category": "生物学",
        "description": "生物の構造や機能、進化、相互作用などを研究する科学領域。"
      },
      {
        "category": "医療",
        "description": "病気の診断・治療・予防など、人の健康を守るための技術や制度を扱う領域。"
      },
      {
        "category": "健康",
        "description": "身体的・精神的な健康維持や促進、医療や保健のアプローチを総合的に扱う領域。"
      },
      {
        "category": "生命科学",
        "description": "生物学やバイオテクノロジーなど、生命現象のメカニズムを解明する領域。"
      },
      {
        "category": "農業",
        "description": "作物や家畜の生産、農地の管理など、食料供給や地域産業に関わる領域。"
      },
      {
        "category": "飲食",
        "description": "食品の開発や安全、調理や食文化などのテーマを含む領域。"
      },
      {
        "category": "エネルギー",
        "description": "電力や燃料などの資源の生成・管理・効率化を扱う領域。"
      },
      {
        "category": "情報技術",
        "description": "コンピューターや通信技術、ネットワークなど、情報の処理・伝達に関わる技術領域。"
      },
      {
        "category": "工学",
        "description": "科学的原理を応用して技術開発・設計を行う領域。"
      },
      {
        "category": "建築",
        "description": "建造物や空間の設計・構造・機能を探求し、実際に形にする領域。"
      },
      {
        "category": "デザイン",
        "description": "目的や機能、美しさを考慮してモノやサービスを創造・設計する領域。"
      },
      {
        "category": "製造",
        "description": "工場生産や製品開発、モノづくりのプロセス・技術を扱う領域。"
      },
      {
        "category": "情報学",
        "description": "情報の構造や処理、システムの設計・運用について体系的に研究する領域。"
      },
      {
        "category": "統計",
        "description": "データの収集・分析・推定など、数量的情報を扱う手法や理論を中心とする領域。"
      },
      {
        "category": "解析",
        "description": "複雑なシステムやデータを多角的に分析・評価する手法や理論を扱う領域。"
      }
    ]
  },
  "文化・芸術・表現": {
    "description": "人間の創造性や歴史・言語、芸術活動など、多様な文化的営みやコミュニケーションの形を扱う領域。",
    "subcategories": [
      {
        "category": "文学",
        "description": "物語・詩・戯曲などの創作や研究、言語表現を重視する芸術領域。"
      },
      {
        "category": "言語",
        "description": "言語そのものの構造や特徴、コミュニケーション手段としての働きを研究する領域。"
      },
      {
        "category": "語学",
        "description": "特定の言語を学習し、運用能力を高める実践的な領域。"
      },
      {
        "category": "歴史",
        "description": "過去の事実や事象を研究し、社会や文化の変遷を理解する領域。"
      },
      {
        "category": "考古学",
        "description": "遺跡や遺物を手がかりに、過去の人類社会の生活・文化を明らかにする研究領域。"
      },
      {
        "category": "文化人類学",
        "description": "世界各地の文化や社会を比較し、人類の多様性や共通点を探究する領域。"
      },
      {
        "category": "芸術",
        "description": "絵画や彫刻、音楽、映像など、あらゆる創造的表現の総称。"
      },
      {
        "category": "ファッション",
        "description": "衣服や装飾、スタイルなど、美的感覚や流行を扱う文化的・商業的領域。"
      },
      {
        "category": "デザイン",
        "description": "機能や意匠、使いやすさなどを考慮してモノや空間を形作る表現領域。"
      },
      {
        "category": "建築",
        "description": "人間の居住や活動空間を構想・設計・実現する総合的な芸術・技術領域。"
      },
      {
        "category": "食文化",
        "description": "食事や調理法、食習慣など、人々の暮らしや歴史・地域性と結びついた文化領域。"
      },
      {
        "category": "娯楽",
        "description": "映画・音楽・ゲームなど、人々を楽しませるためのコンテンツや活動を扱う領域。"
      },
      {
        "category": "サブカルチャー",
        "description": "メインストリームとは異なる独自の趣味やコミュニティを形成するポップカルチャーの一領域。"
      },
      {
        "category": "マスメディア",
        "description": "テレビ・新聞・雑誌・ラジオなど、不特定多数に情報を発信する媒体に関する領域。"
      },
      {
        "category": "ジャーナリズム",
        "description": "報道や取材を通じて客観的・公共的な情報を社会に提供する活動・領域。"
      },
      {
        "category": "パブリック・リレーションズ",
        "description": "企業や団体が社会との関係を良好に保つための広報・コミュニケーション活動を扱う領域。"
      },
      {
        "category": "スポーツ",
        "description": "身体やチームワークを活用した競技・運動、観戦・応援などを含む文化的活動領域。"
      },
      {
        "category": "舞台芸術",
        "description": "演劇やオペラ、ミュージカルなど、ステージ上での総合的な芸術表現を扱う領域。"
      },
      {
        "category": "ダンス",
        "description": "音楽やリズムに合わせて身体表現を行うパフォーマンス芸術領域。"
      },
      {
        "category": "武道",
        "description": "格闘や身体的修練を通じて精神性も重視する武術やスポーツの総称。"
      }
    ]
  },
  "生活・実践・ライフスキル": {
    "description": "日々の暮らしや実践的なスキル、人生の質を高めるための活動や方法論に関する領域。",
    "subcategories": [
      {
        "category": "生活",
        "description": "日常生活や衣食住、暮らし全般の向上を考える領域。"
      },
      {
        "category": "家事",
        "description": "掃除・洗濯・料理など家庭内で行われる作業やその効率化を扱う領域。"
      },
      {
        "category": "育児",
        "description": "子どもの成長や発達を支えるケア・教育・環境作りを扱う領域。"
      },
      {
        "category": "介護",
        "description": "高齢者や障がい者などを支援するためのケアや福祉サービスに関する領域。"
      },
      {
        "category": "住宅",
        "description": "住まいの選択や設備、生活空間の設計・管理などを扱う領域。"
      },
      {
        "category": "DIY",
        "description": "自分で必要なものを作ったり修繕したりするセルフクラフトやメンテナンス活動。"
      },
      {
        "category": "インテリア",
        "description": "部屋や建物の内部空間の美しさや機能性を高めるための装飾やレイアウトを扱う領域。"
      },
      {
        "category": "健康",
        "description": "心身の健康維持や予防、ライフスタイルの改善などを実践的に扱う領域。"
      },
      {
        "category": "美容",
        "description": "外見を整えたり、身体をケアしたりする方法や製品などを扱う領域。"
      },
      {
        "category": "フィットネス",
        "description": "運動や身体活動を通じて健康や体力を向上させる実践的活動。"
      },
      {
        "category": "教育",
        "description": "知識や技能の習得、人格形成を目的とした教え・学びの場や方法に関する領域。"
      },
      {
        "category": "学習",
        "description": "学問や技能の習得を目的とした継続的な学びや勉強法を扱う領域。"
      },
      {
        "category": "資格",
        "description": "特定の職業やスキルを証明するライセンスや免許を取得するための学習・対策。"
      },
      {
        "category": "能力開発",
        "description": "個人の潜在的な力を引き出し、スキルや知識を向上させる方法を扱う領域。"
      },
      {
        "category": "趣味",
        "description": "個人の楽しみやリフレッシュを目的とした活動や関心事を扱う領域。"
      },
      {
        "category": "レジャー",
        "description": "余暇を過ごすための娯楽やリラクゼーション活動に関する領域。"
      },
      {
        "category": "旅行",
        "description": "観光や探検、新しい体験を求めて移動する活動やそのプランニングを扱う領域。"
      },
      {
        "category": "野外活動",
        "description": "キャンプやハイキングなど、屋外でのレジャーやスポーツを中心とした活動。"
      },
      {
        "category": "恋愛",
        "description": "パートナーシップや感情的な結びつき、コミュニケーションに関する領域。"
      },
      {
        "category": "結婚",
        "description": "パートナーとの共同生活や家庭形成、法的契約などを扱う領域。"
      },
      {
        "category": "家族",
        "description": "家族の在り方や家族関係、家庭内の問題やサポートを扱う領域。"
      },
      {
        "category": "人間関係",
        "description": "他者との交流やコミュニケーション、対人スキルを扱う領域。"
      },
      {
        "category": "資産運用",
        "description": "貯蓄や投資、保険などを通じて個人や家族の資産を形成・維持する手法を扱う領域。"
      },
      {
        "category": "ビジネススキル",
        "description": "職場や仕事で必要とされる専門能力や対人能力、業務改善などを扱う領域。"
      },
      {
        "category": "プロジェクトマネジメント",
        "description": "目標達成に向けて組織やリソースを計画・管理する方法論を扱う領域。"
      },
      {
        "category": "問題解決",
        "description": "課題に対して分析・対策・実行を行い、成果を出すための手法を扱う領域。"
      },
      {
        "category": "ビジネススキル",
        "description": "（重複）職業能力やコミュニケーション、リーダーシップなど、仕事で求められる要素を扱う領域。"
      }
    ]
  },
  "心理・精神・内面世界": {
    "description": "人間の心や意識、精神的健康、人生観や価値観など、内面の世界を扱う領域。",
    "subcategories": [
      {
        "category": "心理学",
        "description": "人間の感情や行動、認知などを科学的に研究する領域。"
      },
      {
        "category": "カウンセリング",
        "description": "対話を通じて個人の悩みや問題をサポートし、解決へ導く専門的アプローチ。"
      },
      {
        "category": "メンタルヘルス",
        "description": "心の健康維持や精神疾患の予防・治療などを扱う領域。"
      },
      {
        "category": "哲学",
        "description": "（重複）人間や世界の本質、人生の意味などを理性的に探究する学問領域。"
      },
      {
        "category": "倫理",
        "description": "（重複）内面的・個人的な観点から、行動や判断の善悪・価値基準を考える領域。"
      },
      {
        "category": "死生観",
        "description": "生と死の意味や位置づけを考察し、人間の存在を見つめ直す領域。"
      },
      {
        "category": "分析心理学",
        "description": "ユング心理学を代表とする、人間の深層心理や無意識の構造を探究する領域。"
      },
      {
        "category": "幸せ",
        "description": "ウェルビーイングや人生の満足度、幸福度を高める方法や概念を扱う領域。"
      },
      {
        "category": "クオリティ・オブ・ライフ",
        "description": "人生の質や満足感、暮らしの豊かさを測り高めるための概念を扱う領域。"
      },
      {
        "category": "瞑想",
        "description": "呼吸や意識をコントロールし、心を集中・安定させる実践を扱う領域。"
      },
      {
        "category": "マインドフルネス",
        "description": "いまこの瞬間の感覚や気づきを重視し、ストレス軽減や自己理解に繋げる手法。"
      },
      {
        "category": "動機づけ",
        "description": "行動を起こす原動力や意欲の高め方を分析・実践する領域。"
      },
      {
        "category": "コミュニケーション",
        "description": "対人関係における言語・非言語メッセージの伝達や理解、心理面を含む領域。"
      },
      {
        "category": "人間関係",
        "description": "（重複）個人間の心理的なつながりや交流を扱い、よりよい関係性を模索する領域。"
      }
    ]
  }
}

